CHANGELOG.txt
LICENCE.txt
MANIFEST.in
README.txt
setup.py
google_api_services_helper.egg-info/PKG-INFO
google_api_services_helper.egg-info/SOURCES.txt
google_api_services_helper.egg-info/dependency_links.txt
google_api_services_helper.egg-info/requires.txt
google_api_services_helper.egg-info/top_level.txt
googleapihelper/Credentials.py
googleapihelper/DriveManagement.py
googleapihelper/GmailManagement.py
googleapihelper/SheetsManagement.py
googleapihelper/__init__.py