Metadata-Version: 2.1
Name: google-api-services-helper
Version: 0.0.2
Summary: Work In progress! A package with functionalities to help you develop faster code using google apis
Home-page: 
Author: Dulea Mihai-Alexandru
Author-email: duleasoft@gmail.com
License: MIT
Keywords: api,google,google-sheets,google-drive
Classifier: Development Status :: 1 - Planning
Classifier: Intended Audience :: Developers
Classifier: Operating System :: Microsoft :: Windows
Classifier: Operating System :: POSIX :: Linux
Classifier: Operating System :: MacOS
Classifier: License :: OSI Approved :: MIT License
Classifier: Programming Language :: Python :: 3
License-File: LICENCE.txt
